reqgenz/src/reqgenz.py
reqgenz/test/test_reqgenz.py
reqgenz-0.1.6.dist-info/LICENSE
reqgenz-0.1.6.dist-info/METADATA
reqgenz-0.1.6.dist-info/WHEEL
reqgenz-0.1.6.dist-info/entry_points.txt
reqgenz-0.1.6.dist-info/RECORD
