Metadata-Version: 2.1
Name: reqgenz
Version: 0.1.6
Summary: Requirements Generator Tool: Manage requirements, versioning, and virtual environments for Python projects.
Home-page: https://github.com/webcoderz/reqgenz
Keywords: packaging,dependency,poetry,uv,pip
Author: Cody Webb
Author-email: cody.l.webb@gmail.com
Classifier: Programming Language :: Python :: 2
Classifier: Programming Language :: Python :: 2.7
Classifier: Programming Language :: Python :: 3
Classifier: Programming Language :: Python :: 3.4
Classifier: Programming Language :: Python :: 3.5
Classifier: Programming Language :: Python :: 3.6
Classifier: Programming Language :: Python :: 3.7
Classifier: Programming Language :: Python :: 3.8
Classifier: Programming Language :: Python :: 3.9
Classifier: Programming Language :: Python :: 3.10
Classifier: Programming Language :: Python :: 3.11
Classifier: Programming Language :: Python :: 3.12
Classifier: Topic :: Software Development :: Build Tools
Classifier: Topic :: Software Development :: Libraries :: Python Modules
Project-URL: Repository, https://github.com/webcoderz/reqgenz
